odoo/addons/stock_picking_return_refund_option/README.rst
odoo/addons/stock_picking_return_refund_option/__init__.py
odoo/addons/stock_picking_return_refund_option/__manifest__.py
odoo/addons/stock_picking_return_refund_option/i18n/es.po
odoo/addons/stock_picking_return_refund_option/i18n/stock_picking_return_refund_option.pot
odoo/addons/stock_picking_return_refund_option/models/__init__.py
odoo/addons/stock_picking_return_refund_option/models/stock_move.py
odoo/addons/stock_picking_return_refund_option/models/stock_picking.py
odoo/addons/stock_picking_return_refund_option/readme/CONTRIBUTORS.rst
odoo/addons/stock_picking_return_refund_option/readme/DESCRIPTION.rst
odoo/addons/stock_picking_return_refund_option/readme/INSTALL.rst
odoo/addons/stock_picking_return_refund_option/readme/USAGE.rst
odoo/addons/stock_picking_return_refund_option/static/description/icon.png
odoo/addons/stock_picking_return_refund_option/static/description/index.html
odoo/addons/stock_picking_return_refund_option/tests/__init__.py
odoo/addons/stock_picking_return_refund_option/tests/test_stock_picking_return_refund_options.py
odoo/addons/stock_picking_return_refund_option/views/stock_picking_view.xml
odoo13_addon_stock_picking_return_refund_option-13.0.1.0.2.dist-info/METADATA
odoo13_addon_stock_picking_return_refund_option-13.0.1.0.2.dist-info/WHEEL
odoo13_addon_stock_picking_return_refund_option-13.0.1.0.2.dist-info/top_level.txt
odoo13_addon_stock_picking_return_refund_option-13.0.1.0.2.dist-info/RECORD
